ezmsg/baseproc/__init__.py
ezmsg/baseproc/__version__.py
ezmsg/baseproc/clock.py
ezmsg/baseproc/clockdriven.py
ezmsg/baseproc/composite.py
ezmsg/baseproc/counter.py
ezmsg/baseproc/processor.py
ezmsg/baseproc/protocols.py
ezmsg/baseproc/stateful.py
ezmsg/baseproc/units.py
ezmsg/baseproc/util/__init__.py
ezmsg/baseproc/util/asio.py
ezmsg/baseproc/util/message.py
ezmsg/baseproc/util/profile.py
ezmsg/baseproc/util/typeresolution.py
ezmsg_baseproc-1.2.1.dist-info/METADATA
ezmsg_baseproc-1.2.1.dist-info/WHEEL
ezmsg_baseproc-1.2.1.dist-info/licenses/LICENSE
ezmsg_baseproc-1.2.1.dist-info/RECORD
