Metadata-Version: 2.4
Name: ezmsg-baseproc
Version: 1.2.1
Summary: Base processor classes and protocols for ezmsg signal processing pipelines
Author-email: Griffin Milsap <griffin.milsap@gmail.com>, Preston Peranich <pperanich@gmail.com>, Chadwick Boulay <chadwick.boulay@gmail.com>, Kyle McGraw <kmcgraw@blackrockneuro.com>
License-Expression: MIT
License-File: LICENSE
Requires-Python: >=3.10
Requires-Dist: ezmsg[axisarray]>=3.6.0
Requires-Dist: typing-extensions>=4.0.0
